dhl/__init__.py
dhl/schema.py
dhl/wsdl/3.1/geschaeftskundenversand-api-3.1.8-schema-bcs_base.xsd
dhl/wsdl/3.1/geschaeftskundenversand-api-3.1.8-schema-cis_base.xsd
dhl/wsdl/3.1/production.wsdl
dhl/wsdl/3.1/test.wsdl
dhl/wsdl/3.3.0/geschaeftskundenversand-api-3.3.0-schema-bcs_base.xsd
dhl/wsdl/3.3.0/geschaeftskundenversand-api-3.3.0-schema-cis_base.xsd
dhl/wsdl/3.3.0/production.wsdl
dhl/wsdl/3.3.0/test.wsdl
dhl/wsdl/3.4.0/geschaeftskundenversand-api-3.4.0-schema-bcs_base.xsd
dhl/wsdl/3.4.0/geschaeftskundenversand-api-3.4.0-schema-cis_base.xsd
dhl/wsdl/3.4.0/production.wsdl
dhl/wsdl/3.4.0/test.wsdl
python_dhl_germany-0.3.4.14.dist-info/METADATA
python_dhl_germany-0.3.4.14.dist-info/WHEEL
python_dhl_germany-0.3.4.14.dist-info/licenses/LICENSE
python_dhl_germany-0.3.4.14.dist-info/RECORD
