Metadata-Version: 2.1
Name: python_dhl_germany
Version: 0.3.4.14
Summary: Python Lib for DHL SOAP API (Germany)
Author-email: Johannes Eimer <johannes.eimer@jep-dev.com>
License-Expression: MIT
License-File: LICENSE
Keywords: DHL,Python
Requires-Python: >=3.9
Requires-Dist: requests==2.31.0
Requires-Dist: zeep==4.2.1
